longsora/.DS_Store
longsora/__init__.py
longsora/_client.py
longsora/_utils/__init__.py
longsora/_utils/jobs_utils.py
longsora/_utils/prompt_utils.py
longsora/_utils/prompts.py
longsora/_utils/video_duration_utils.py
longsora/_utils/video_utils.py
longsora/openai/.DS_Store
longsora/openai/__init__.py
longsora/openai/__main__.py
longsora/openai/_base_client.py
longsora/openai/_client.py
longsora/openai/_compat.py
longsora/openai/_constants.py
longsora/openai/_exceptions.py
longsora/openai/_extras/__init__.py
longsora/openai/_extras/_common.py
longsora/openai/_extras/numpy_proxy.py
longsora/openai/_extras/pandas_proxy.py
longsora/openai/_extras/sounddevice_proxy.py
longsora/openai/_files.py
longsora/openai/_legacy_response.py
longsora/openai/_models.py
longsora/openai/_module_client.py
longsora/openai/_qs.py
longsora/openai/_resource.py
longsora/openai/_response.py
longsora/openai/_streaming.py
longsora/openai/_types.py
longsora/openai/_utils/__init__.py
longsora/openai/_utils/_compat.py
longsora/openai/_utils/_datetime_parse.py
longsora/openai/_utils/_logs.py
longsora/openai/_utils/_proxy.py
longsora/openai/_utils/_reflection.py
longsora/openai/_utils/_resources_proxy.py
longsora/openai/_utils/_streams.py
longsora/openai/_utils/_sync.py
longsora/openai/_utils/_transform.py
longsora/openai/_utils/_typing.py
longsora/openai/_utils/_utils.py
longsora/openai/_version.py
longsora/openai/cli/.DS_Store
longsora/openai/cli/__init__.py
longsora/openai/cli/_api/.DS_Store
longsora/openai/cli/_api/__init__.py
longsora/openai/cli/_api/_main.py
longsora/openai/cli/_api/audio.py
longsora/openai/cli/_api/chat/__init__.py
longsora/openai/cli/_api/chat/completions.py
longsora/openai/cli/_api/completions.py
longsora/openai/cli/_api/files.py
longsora/openai/cli/_api/fine_tuning/__init__.py
longsora/openai/cli/_api/fine_tuning/jobs.py
longsora/openai/cli/_api/image.py
longsora/openai/cli/_api/models.py
longsora/openai/cli/_cli.py
longsora/openai/cli/_errors.py
longsora-0.1.5.dist-info/WHEEL
longsora-0.1.5.dist-info/METADATA
longsora-0.1.5.dist-info/RECORD
