Metadata-Version: 2.3
Name: longsora
Version: 0.1.5
Summary: Add your description here
Author: llinkedlist771
License: MIT License
Classifier: Programming Language :: Python :: 3
Classifier: Programming Language :: Python :: 3.12
Classifier: License :: OSI Approved :: MIT License
Classifier: Intended Audience :: Developers
Classifier: Topic :: Scientific/Engineering :: Artificial Intelligence
Requires-Dist: distro>=1.9.0
Requires-Dist: ffmpeg-python>=0.2.0
Requires-Dist: httpx>=0.28.1
Requires-Dist: jiter>=0.11.0
Requires-Dist: loguru>=0.7.3
Requires-Dist: opencv-python>=4.12.0.88
Requires-Dist: pydantic>=2.12.0
Requires-Dist: typing-extensions>=4.15.0
Requires-Dist: ruff>=0.6.0 ; extra == 'dev'
Requires-Dist: mypy>=1.10.0 ; extra == 'dev'
Requires-Dist: pytest>=8.0.0 ; extra == 'dev'
Requires-Python: >=3.12
Project-URL: Homepage, https://github.com/linkedlist771/LongSoraGen
Project-URL: Issues, https://github.com/linkedlist771/LongSoraGen/issues
Project-URL: Source, https://github.com/linkedlist771/LongSoraGen
Provides-Extra: dev
